examples/__init__.py
examples/advanced_usage.py
examples/basic_usage.py
examples/constants_usage.py
paygent_sdk/__init__.py
paygent_sdk/client.py
paygent_sdk/constants.py
paygent_sdk/models.py
paygent_sdk/voice_client.py
paygent_sdk/wrappers/__init__.py
paygent_sdk/wrappers/anthropic_wrapper.py
paygent_sdk/wrappers/gemini_wrapper.py
paygent_sdk/wrappers/langchain_wrapper.py
paygent_sdk/wrappers/mistral_wrapper.py
paygent_sdk/wrappers/openai_wrapper.py
paygent_sdk-2.0.0.dist-info/licenses/LICENSE
tests/__init__.py
tests/test_client.py
paygent_sdk-2.0.0.dist-info/METADATA
paygent_sdk-2.0.0.dist-info/WHEEL
paygent_sdk-2.0.0.dist-info/top_level.txt
paygent_sdk-2.0.0.dist-info/RECORD
