Metadata-Version: 2.4
Name: paygent-sdk
Version: 2.0.0
Summary: Official Python SDK for Paygent - Track AI usage and costs across multiple providers (OpenAI, Anthropic, Google, DeepSeek, etc.)
Home-page: https://github.com/paygent/paygent-sdk-python
Author: Paygent
Author-email: Paygent Team <support@paygent.com>
Maintainer-email: Paygent Team <support@paygent.com>
License: MIT
Project-URL: Homepage, https://paygent.com
Project-URL: Repository, https://github.com/paygent/paygent-sdk-python
Project-URL: Documentation, https://github.com/paygent/paygent-sdk-python#readme
Project-URL: Bug Tracker, https://github.com/paygent/paygent-sdk-python/issues
Project-URL: Changelog, https://github.com/paygent/paygent-sdk-python/releases
Project-URL: Source Code, https://github.com/paygent/paygent-sdk-python
Keywords: paygent,sdk,ai,llm,usage,tracking,costs,openai,anthropic,claude,gpt,gemini,deepseek,token-counting,cost-calculation,api-integration
Classifier: Development Status :: 5 - Production/Stable
Classifier: Intended Audience :: Developers
Classifier: License :: OSI Approved :: MIT License
Classifier: Operating System :: OS Independent
Classifier: Programming Language :: Python :: 3
Classifier: Programming Language :: Python :: 3.7
Classifier: Programming Language :: Python :: 3.8
Classifier: Programming Language :: Python :: 3.9
Classifier: Programming Language :: Python :: 3.10
Classifier: Programming Language :: Python :: 3.11
Classifier: Programming Language :: Python :: 3.12
Classifier: Topic :: Software Development :: Libraries :: Python Modules
Classifier: Topic :: Internet :: WWW/HTTP :: Dynamic Content
Classifier: Topic :: Scientific/Engineering :: Artificial Intelligence
Classifier: Typing :: Typed
Requires-Python: >=3.7
License-File: LICENSE
Requires-Dist: requests>=2.25.0
Requires-Dist: urllib3>=1.26.0
Requires-Dist: tiktoken>=0.5.0
Provides-Extra: dev
Requires-Dist: pytest>=6.0; extra == "dev"
Requires-Dist: pytest-cov>=2.0; extra == "dev"
Requires-Dist: black>=21.0; extra == "dev"
Requires-Dist: flake8>=3.8; extra == "dev"
Requires-Dist: mypy>=0.800; extra == "dev"
Dynamic: author
Dynamic: home-page
Dynamic: license-file
Dynamic: requires-python
